Metadata-Version: 2.1
Name: py-trello-api
Version: 0.20.0
Summary: Python wrapper around the Trello API (Provisional version)
Home-page: https://github.com/Konano/py-trello-api
Author: Konano
Author-email: nanoapezlk@gmail.com
License: BSD License
Download-URL: https://github.com/Konano/py-trello-api
Keywords: python
Platform: UNKNOWN
Classifier: Development Status :: 4 - Beta
Classifier: Intended Audience :: Developers
Classifier: License :: OSI Approved :: BSD License
Classifier: Operating System :: OS Independent
Classifier: Programming Language :: Python
Classifier: Programming Language :: Python :: 2
Classifier: Programming Language :: Python :: 2.7
Classifier: Programming Language :: Python :: 3
Classifier: Programming Language :: Python :: 3.3
Requires-Dist: python-dateutil
Requires-Dist: pytz
Requires-Dist: requests
Requires-Dist: requests-oauthlib (>=0.4.1)
